Tweetl/__init__.py
Tweetl/cleansing_tweets.py
Tweetl/get_tweets.py
Tweetl-0.0.7.dist-info/LICENSE
Tweetl-0.0.7.dist-info/METADATA
Tweetl-0.0.7.dist-info/WHEEL
Tweetl-0.0.7.dist-info/top_level.txt
Tweetl-0.0.7.dist-info/RECORD
