Metadata-Version: 2.1
Name: Tweetl
Version: 0.0.7
Summary: A package to do everything from getting tweets to pre-processing
Home-page: https://github.com/deepblue-ts/Tweetl
Author: deepblue
Author-email: main@deepbluets.page
License: MIT
Keywords: natural language processing,twitter,cleansing
Platform: UNKNOWN
Classifier: License :: OSI Approved :: MIT License
Classifier: Programming Language :: Python :: 3
Classifier: Programming Language :: Python :: 3.4
Classifier: Programming Language :: Python :: 3.5
Classifier: Programming Language :: Python :: 3.6
Classifier: Programming Language :: Python :: 3.7
Classifier: Programming Language :: Python :: 3.8
Requires-Dist: as (==0.1)
Requires-Dist: certifi (==2020.4.5.1)
Requires-Dist: chardet (==3.0.4)
Requires-Dist: emoji (==0.5.4)
Requires-Dist: idna (==2.9)
Requires-Dist: mojimoji (==0.0.11)
Requires-Dist: neologdn (==0.4)
Requires-Dist: numpy
Requires-Dist: oauthlib (==3.1.0)
Requires-Dist: pandas
Requires-Dist: pd (==0.0.1)
Requires-Dist: PySocks (==1.7.1)
Requires-Dist: python-dateutil (==2.8.1)
Requires-Dist: pytz (==2020.1)
Requires-Dist: requests (==2.23.0)
Requires-Dist: requests-oauthlib (==1.3.0)
Requires-Dist: six (==1.14.0)
Requires-Dist: tweepy (==3.8.0)
Requires-Dist: urllib3 (==1.25.9)
